netbox_systems/__init__.py
netbox_systems/api/__init__.py
netbox_systems/api/serializers.py
netbox_systems/api/urls.py
netbox_systems/api/views.py
netbox_systems/filtersets.py
netbox_systems/forms.py
netbox_systems/migrations/__init__.py
netbox_systems/models.py
netbox_systems/navigation.py
netbox_systems/search.py
netbox_systems/tables.py
netbox_systems/template_content.py
netbox_systems/templates/netbox_systems/pl_systems.html
netbox_systems/templates/netbox_systems/pl_systems_edit.html
netbox_systems/templates/netbox_systems/pl_systems_include.html
netbox_systems/templates/netbox_systems/systems_edit.html
netbox_systems/urls.py
netbox_systems/views.py
netbox_systems-0.1.1.dist-info/LICENSE
netbox_systems-0.1.1.dist-info/METADATA
netbox_systems-0.1.1.dist-info/WHEEL
netbox_systems-0.1.1.dist-info/RECORD
