Metadata-Version: 2.1
Name: netbox-systems
Version: 0.1.1
Summary: 
Author: izakharov
Author-email: ilya.zakharov@domrf.ru
Requires-Python: >=3.10,<4.0
Classifier: Programming Language :: Python :: 3
Classifier: Programming Language :: Python :: 3.10
Classifier: Programming Language :: Python :: 3.11
